{
  "strict": true,
  "nodeModulesDir": "none",
  "lock": false,
  "compilerOptions": {
    "strict": true,
    "lib": ["deno.ns", "webworker", "dom", "dom.iterable", "dom.asynciterable"],
    "jsx": "react-jsx",
    "jsxImportSource": "preact",
    "useUnknownInCatchVariables": true
  },
  "lint": {
    "include": ["src/"],
    "rules": {
      "tags": ["recommended"],
      "include": ["no-non-null-assertion"]
    }
  },
  "fmt": {
    "include": ["src/"],
    "semiColons": false,
    "singleQuote": true
  },
  "tasks": {
    "build": "deno run --allow-run --allow-read --allow-net --allow-write --allow-env --watch=src build.ts",
    "serve": "deno run --allow-net --allow-read --allow-env --watch=./src server.ts"
  },
  "imports": {
    "@/": "./src/",
    "@/global.css": "./src/types/css.d.ts",
    "@/ui-components/btn/btn.module.css": "./src/types/css.module.d.ts",
    "@/pages/code/code.module.css": "./src/types/css.module.d.ts",
    "@/pages/home/home.module.css": "./src/types/css.module.d.ts",
    "@preact/signals": "https://esm.sh/*@preact/signals@2.0.0",
    "@preact/signals-core": "https://esm.sh/*@preact/signals-core@1.8.0",
    "@std/assert": "jsr:@std/assert",
    "@std/dotenv": "jsr:@std/dotenv",
    "preact": "https://esm.sh/*preact@10.25.4",
    "preact/": "https://esm.sh/*preact@10.25.4/"
  }
}

